laravel_versions/__init__.py
laravel_versions/laravel_versions.py
laravel_versions/py.typed
laravel_versions/types.py
laravel_versions_sdk-1.0.0.dist-info/METADATA
laravel_versions_sdk-1.0.0.dist-info/WHEEL
laravel_versions_sdk-1.0.0.dist-info/licenses/LICENSE.md
laravel_versions_sdk-1.0.0.dist-info/RECORD
