Metadata-Version: 2.1
Name: laravel-versions-sdk
Version: 1.0.0
Summary: Laravel Versions Python SDK
Project-URL: Source Code, https://github.com/owenvoke/laravel-versions-python-sdk
Project-URL: Issues, https://github.com/owenvoke/laravel-versions-python-sdk/issues
Author-email: Owen Voke <development@voke.dev>
License-Expression: MIT
License-File: LICENSE.md
Keywords: laravel,sdk,versions
Classifier: Intended Audience :: Developers
Classifier: License :: OSI Approved :: MIT License
Classifier: Programming Language :: Python :: 3 :: Only
Requires-Python: >=3.11.0
Requires-Dist: requests>=2.28.1
